drf_error_handler/__init__.py
drf_error_handler/apps.py
drf_error_handler/exceptions.py
drf_error_handler/formatter.py
drf_error_handler/handler.py
drf_error_handler/openapi.py
drf_error_handler/openapi_hooks.py
drf_error_handler/openapi_serializers.py
drf_error_handler/openapi_utils.py
drf_error_handler/openapi_validation_errors.py
drf_error_handler/py.typed
drf_error_handler/settings.py
drf_error_handler/types.py
drf_error_handler-0.15.1.dist-info/LICENSE
drf_error_handler-0.15.1.dist-info/WHEEL
drf_error_handler-0.15.1.dist-info/METADATA
drf_error_handler-0.15.1.dist-info/RECORD
