Metadata-Version: 2.1
Name: drf-error-handler
Version: 0.15.1
Summary: Standardize your API error responses.
Keywords: standardized errors,errors formatter,django rest framework,exception handler
Author: Ghazi Abbassi, Nazar Korchizhinskiy
Requires-Python: >=3.8
Classifier: Intended Audience :: Developers
Classifier: License :: OSI Approved :: MIT License
Classifier: Programming Language :: Python :: 3
Classifier: Programming Language :: Python :: 3.8
Classifier: Programming Language :: Python :: 3.9
Classifier: Programming Language :: Python :: 3.10
Classifier: Programming Language :: Python :: 3.11
Classifier: Programming Language :: Python :: 3.12
Requires-Dist: django >=2.2
Requires-Dist: djangorestframework >=3.9
Requires-Dist: pre-commit ; extra == "dev"
Requires-Dist: sphinx!=5.2.0.post0 ; extra == "doc"
Requires-Dist: sphinx-autobuild ; extra == "doc"
Requires-Dist: sphinx-rtd-theme>=1.1.0 ; extra == "doc"
Requires-Dist: myst-parser ; extra == "doc"
Requires-Dist: drf-spectacular>=0.27.0 ; extra == "openapi"
Requires-Dist: inflection ; extra == "openapi"
Requires-Dist: flit ; extra == "release"
Requires-Dist: keyring ; extra == "release"
Requires-Dist: tbump ; extra == "release"
Requires-Dist: tox ; extra == "test"
Requires-Dist: tox-gh-actions ; extra == "test"
Project-URL: Changelog, https://github.com/korchizhinskiy/drf-error-handler/releases
Project-URL: Code, https://github.com/korchizhinskiy/drf-error-handler
Project-URL: Documentation, https://drf-error-handler.readthedocs.io/en/latest/
Project-URL: Homepage, https://github.com/korchizhinskiy/drf-error-handler
Project-URL: Issues, https://github.com/korchizhinskiy/drf-error-handler/issues
Provides-Extra: dev
Provides-Extra: doc
Provides-Extra: openapi
Provides-Extra: release
Provides-Extra: test
